archspec/__init__.py
archspec/cli.py
archspec/cpu/__init__.py
archspec/cpu/alias.py
archspec/cpu/detect.py
archspec/cpu/microarchitecture.py
archspec/cpu/schema.py
archspec/json/.git
archspec/json/.github/workflows/validation.yml
archspec/json/.pytest_cache/.gitignore
archspec/json/.pytest_cache/CACHEDIR.TAG
archspec/json/.pytest_cache/README.md
archspec/json/.pytest_cache/v/cache/nodeids
archspec/json/.pytest_cache/v/cache/stepwise
archspec/json/COPYRIGHT
archspec/json/LICENSE-APACHE
archspec/json/LICENSE-MIT
archspec/json/NOTICE
archspec/json/README.md
archspec/json/cpu/microarchitectures.json
archspec/json/cpu/microarchitectures_schema.json
archspec/json/tests/targets/bgq-rhel6-power7
archspec/json/tests/targets/darwin-bigsur-m1
archspec/json/tests/targets/darwin-mojave-haswell
archspec/json/tests/targets/darwin-mojave-ivybridge
archspec/json/tests/targets/darwin-mojave-skylake
archspec/json/tests/targets/darwin-monterey-m1
archspec/json/tests/targets/darwin-monterey-m2
archspec/json/tests/targets/linux-amazon-cortex_a72
archspec/json/tests/targets/linux-amazon-neoverse_n1
archspec/json/tests/targets/linux-amazon-neoverse_v1
archspec/json/tests/targets/linux-asahi-m1
archspec/json/tests/targets/linux-asahi-m2
archspec/json/tests/targets/linux-centos7-cascadelake
archspec/json/tests/targets/linux-centos7-power8le
archspec/json/tests/targets/linux-centos7-thunderx2
archspec/json/tests/targets/linux-rhel6-piledriver
archspec/json/tests/targets/linux-rhel7-broadwell
archspec/json/tests/targets/linux-rhel7-haswell
archspec/json/tests/targets/linux-rhel7-ivybridge
archspec/json/tests/targets/linux-rhel7-skylake_avx512
archspec/json/tests/targets/linux-rhel7-x86_64_v3
archspec/json/tests/targets/linux-rhel7-zen
archspec/json/tests/targets/linux-scientific7-k10
archspec/json/tests/targets/linux-scientific7-piledriver
archspec/json/tests/targets/linux-scientificfermi6-bulldozer
archspec/json/tests/targets/linux-scientificfermi6-piledriver
archspec-0.2.0.dist-info/entry_points.txt
archspec-0.2.0.dist-info/WHEEL
archspec-0.2.0.dist-info/METADATA
archspec-0.2.0.dist-info/RECORD
