Metadata-Version: 2.1
Name: archspec
Version: 0.2.0
Summary: A library to query system architecture
Home-page: https://github.com/archspec/archspec
License: Apache-2.0 OR MIT
Author: archspec developers
Author-email: maintainers@spack.io
Maintainer: Greg Becker
Maintainer-email: maintainers@spack.io
Requires-Python: >=3.6, !=2.7.*, !=3.0.*, !=3.1.*, !=3.2.*, !=3.3.*, !=3.4.*, !=3.5.*
Classifier: Development Status :: 3 - Alpha
Classifier: Intended Audience :: Developers
Classifier: Intended Audience :: Information Technology
Classifier: Intended Audience :: Science/Research
Classifier: License :: Other/Proprietary License
Classifier: Operating System :: MacOS
Classifier: Operating System :: POSIX :: Linux
Classifier: Operating System :: Unix
Classifier: Programming Language :: Python :: 3
Classifier: Programming Language :: Python :: 3.7
Classifier: Programming Language :: Python :: 3.8
Classifier: Programming Language :: Python :: 3.9
Classifier: Programming Language :: Python :: 3.10
Classifier: Programming Language :: Python :: 3.11
Requires-Dist: click (>=8,<9)
Project-URL: Documentation, https://archspec.readthedocs.io
Project-URL: Repository, https://github.com/archspec/archspec.git
